README.md
bdct/__init__.py
bdct/bd_model.py
bdct/bdct_model.py
bdct/bdsky_model.py
bdct/formulas.py
bdct/model_distinguisher.py
bdct/parameter_estimator.py
bdct/tree_manager.py
bdct-0.1.28.dist-info/LICENSE
bdct-0.1.28.dist-info/METADATA
bdct-0.1.28.dist-info/WHEEL
bdct-0.1.28.dist-info/entry_points.txt
bdct-0.1.28.dist-info/top_level.txt
bdct-0.1.28.dist-info/RECORD
