Metadata-Version: 2.2
Name: bdct
Version: 0.1.28
Summary: Maximum likelihood estimation of BD, BD-CT(1) and BDSKY parameters from phylogenetic trees.
Home-page: https://github.com/evolbioinfo/bdct
Author: Anna Zhukova
Author-email: anna.zhukova@pasteur.fr
Keywords: phylogenetics,birth-death model,birth-death skyline,partner notification,contact tracing,BD,BD-CT,BDSKY
Classifier: Development Status :: 4 - Beta
Classifier: Environment :: Console
Classifier: Intended Audience :: Developers
Classifier: Topic :: Scientific/Engineering :: Bio-Informatics
Classifier: Topic :: Software Development
Classifier: Topic :: Software Development :: Libraries :: Python Modules
Requires: six
Requires: ete3
Requires: numpy
Requires: scipy
Requires: sympy
Requires: biopython
License-File: LICENSE
Requires-Dist: six
Requires-Dist: ete3
Requires-Dist: numpy
Requires-Dist: scipy
Requires-Dist: sympy
Requires-Dist: biopython
Dynamic: author
Dynamic: author-email
Dynamic: classifier
Dynamic: description
Dynamic: description-content-type
Dynamic: home-page
Dynamic: keywords
Dynamic: requires
Dynamic: requires-dist
Dynamic: summary
